mint/__init__.py
mint/mint.py
mint/mint_host.py
mintfsh-0.1.8.dist-info/licenses/LICENSE
mintfsh-0.1.8.dist-info/METADATA
mintfsh-0.1.8.dist-info/WHEEL
mintfsh-0.1.8.dist-info/entry_points.txt
mintfsh-0.1.8.dist-info/top_level.txt
mintfsh-0.1.8.dist-info/RECORD
