Metadata-Version: 2.4
Name: mintfsh
Version: 0.1.8
Summary: Mint is a terminal-based file sharing service, with support for custom mirrors, rich JSON config, and more.
Author: giacomosm
Author-email: giacomosm@proton.me
License: BSD-2-Clause
Classifier: License :: OSI Approved :: BSD License
Classifier: Programming Language :: Python :: 3
Classifier: Operating System :: OS Independent
License-File: LICENSE
Requires-Dist: flask>=2.0.0
Dynamic: author
Dynamic: author-email
Dynamic: classifier
Dynamic: description
Dynamic: description-content-type
Dynamic: license
Dynamic: license-file
Dynamic: requires-dist
Dynamic: summary
